Metadata-Version: 2.1
Name: scrapper-cf
Version: 1.0.5
Summary: This is one of the many packages that Codefree.io will release. This Packages is aimed at speeding up making of scrappers.
Home-page: https://test.pypi.org/manage/project/scrapper-cf/release/1.0.12/
Author: Codefree.io
Author-email: wilson@codefree.io
License: MIT
Platform: UNKNOWN
Classifier: License :: OSI Approved :: MIT License
Classifier: Programming Language :: Python :: 3
Requires-Python: >3.5
